server.py
ado/__init__.py
ado/client.py
ado/errors.py
ado/helpers.py
ado/models.py
ado/py.typed
ado/resources.py
ado/tools.py
ado/pipelines/__init__.py
ado/pipelines/builds.py
ado/pipelines/logs.py
ado/pipelines/pipelines.py
ado_mcp_raboley-0.0.1.dist-info/METADATA
ado_mcp_raboley-0.0.1.dist-info/WHEEL
ado_mcp_raboley-0.0.1.dist-info/entry_points.txt
ado_mcp_raboley-0.0.1.dist-info/top_level.txt
ado_mcp_raboley-0.0.1.dist-info/RECORD
